update_gene_symbols_hgnc/__init__.py
update_gene_symbols_hgnc/_nbdev.py
update_gene_symbols_hgnc/core.py
update_gene_symbols_hgnc-0.0.1.dist-info/LICENSE
update_gene_symbols_hgnc-0.0.1.dist-info/METADATA
update_gene_symbols_hgnc-0.0.1.dist-info/WHEEL
update_gene_symbols_hgnc-0.0.1.dist-info/entry_points.txt
update_gene_symbols_hgnc-0.0.1.dist-info/top_level.txt
update_gene_symbols_hgnc-0.0.1.dist-info/RECORD
